dayangpy
