Metadata-Version: 1.0
Name: dayang-sdk-python
Version: 0.4
Summary: dayang sdk python
Home-page: https://github.com/wqfff/dayang-sdk-python.git
Author: wqf
Author-email: UNKNOWN
License: UNKNOWN
Platform: UNKNOWN
